time_tracker/__init__.py
time_tracker/admin.py
time_tracker/apps.py
time_tracker/forms.py
time_tracker/models.py
time_tracker/tests.py
time_tracker/urls.py
time_tracker/views.py
time_tracker/migrations/0001_initial.py
time_tracker/migrations/__init__.py
time_tracker/utils/DynamoDB.py
time_tracker/utils/__init__.py
time_tracker/utils/cloudwatch_log.py
time_tracker/utils/notifications.py
time_tracker/utils/s3_storage.py
time_tracker/utils/sqs_helper.py
tracker/__init__.py
tracker/settings.py
tracker/urls.py
tracker/wsgi.py
tracker/migrations/0001_initial.py
tracker/migrations/0002_project_worksession.py
tracker/migrations/__init__.py
Final_CPP_Project-0.4.7.dist-info/METADATA
Final_CPP_Project-0.4.7.dist-info/WHEEL
Final_CPP_Project-0.4.7.dist-info/top_level.txt
Final_CPP_Project-0.4.7.dist-info/RECORD
